hashkeep.py
hashkeep-1.0.1.dist-info/licenses/LICENSE
hashkeep-1.0.1.dist-info/METADATA
hashkeep-1.0.1.dist-info/WHEEL
hashkeep-1.0.1.dist-info/entry_points.txt
hashkeep-1.0.1.dist-info/top_level.txt
hashkeep-1.0.1.dist-info/RECORD
