Metadata-Version: 2.4
Name: hashkeep
Version: 1.0.1
Summary: Simple utility to hash the contents of files and store hashes in a cache for quick repeat hashing
Author-email: Nathan Shearer <shearern@gmail.com>
License-Expression: MIT AND (Apache-2.0 OR BSD-2-Clause)
Project-URL: Repository, https://gitlab.com/shearern/hashkeep
Requires-Python: >=3.7
License-File: LICENSE
Requires-Dist: diskcache
Dynamic: license-file
